cterasdk/__init__.py
cterasdk/settings.py
cterasdk/settings.yml
cterasdk/version.py
cterasdk/asynchronous/__init__.py
cterasdk/asynchronous/core/__init__.py
cterasdk/asynchronous/core/base_command.py
cterasdk/asynchronous/core/cloudfs.py
cterasdk/asynchronous/core/iterator.py
cterasdk/asynchronous/core/login.py
cterasdk/asynchronous/core/notifications.py
cterasdk/asynchronous/core/portals.py
cterasdk/asynchronous/core/query.py
cterasdk/asynchronous/core/settings.py
cterasdk/asynchronous/core/tasks.py
cterasdk/asynchronous/core/types.py
cterasdk/asynchronous/core/users.py
cterasdk/asynchronous/core/files/__init__.py
cterasdk/asynchronous/core/files/browser.py
cterasdk/asynchronous/core/files/io.py
cterasdk/asynchronous/edge/__init__.py
cterasdk/asynchronous/edge/base_command.py
cterasdk/asynchronous/edge/login.py
cterasdk/asynchronous/edge/files/__init__.py
cterasdk/asynchronous/edge/files/browser.py
cterasdk/asynchronous/edge/files/io.py
cterasdk/audit/__init__.py
cterasdk/audit/postman.py
cterasdk/cio/__init__.py
cterasdk/cio/actions.py
cterasdk/cio/common.py
cterasdk/cio/core/__init__.py
cterasdk/cio/core/commands.py
cterasdk/cio/core/types.py
cterasdk/cio/edge/__init__.py
cterasdk/cio/edge/commands.py
cterasdk/cio/edge/types.py
cterasdk/clients/__init__.py
cterasdk/clients/async_requests.py
cterasdk/clients/base.py
cterasdk/clients/clients.py
cterasdk/clients/common.py
cterasdk/clients/decorators.py
cterasdk/clients/errors.py
cterasdk/clients/settings.py
cterasdk/clients/tracers/__init__.py
cterasdk/clients/tracers/postman.py
cterasdk/clients/tracers/requests.py
cterasdk/clients/tracers/session.py
cterasdk/common/__init__.py
cterasdk/common/datetime_utils.py
cterasdk/common/enum.py
cterasdk/common/item.py
cterasdk/common/modules.py
cterasdk/common/object.py
cterasdk/common/types.py
cterasdk/common/utils.py
cterasdk/convert/__init__.py
cterasdk/convert/deserializers.py
cterasdk/convert/serializers.py
cterasdk/convert/types.py
cterasdk/core/__init__.py
cterasdk-2.20.27.dist-info/licenses/LICENSE
cterasdk-2.20.27.dist-info/METADATA
cterasdk-2.20.27.dist-info/WHEEL
cterasdk-2.20.27.dist-info/entry_points.txt
cterasdk-2.20.27.dist-info/top_level.txt
cterasdk-2.20.27.dist-info/RECORD
