Metadata-Version: 2.4
Name: cterasdk
Version: 2.20.27
Author-email: Saimon Michelson <saimon@ctera.com>
Maintainer-email: CTERA Networks Ltd <info@ctera.com>
License-Expression: Apache-2.0
Project-URL: Homepage, https://pypi.org/project/cterasdk/
Project-URL: Bug Tracker, https://github.com/ctera/ctera-python-sdk/issues
Project-URL: Documentation, https://ctera-python-sdk.readthedocs.io/en/latest/
Project-URL: Source Code, https://github.com/ctera/ctera-python-sdk
Classifier: Development Status :: 5 - Production/Stable
Classifier: Intended Audience :: Developers
Classifier: Operating System :: OS Independent
Classifier: Programming Language :: Python :: 3
Classifier: Topic :: Software Development :: Libraries :: Python Modules
Requires-Python: >=3.10
License-File: LICENSE
Requires-Dist: pyyaml
Requires-Dist: aiohttp>=3.12.14
Requires-Dist: aiofiles
Requires-Dist: cryptography
Requires-Dist: packaging
Requires-Dist: python-snappy
Dynamic: license-file
